[
  {
    "app": "File Manager+",
    "creator": "Alphainventor",
    "packageName": "com.alphainventor.filemanager",
    "category": "Utilities",
    "link": "https://raw.githubusercontent.com/LunaDevPH/AppStoreMirror/main/alphainventor_filemanagerplus.apk",
    "description": "Advanced file management tool with network storage support and Android 11+ compatibility.",
    "icon": "https://raw.githubusercontent.com/LunaDevPH/AppStoreMirror/main/alphainventor_filemanagerplus.png",
    "isVerified": true,
    "isFeatured": true,
    "isSmall": false,
    "hasPreview": false,
    "previewLink": "",
    "version": "3.6.8",
    "minAndroid": 5,
    "targetAndroid": 15
  },
  {
    "app": "Magisk",
    "creator": "topjohnwu",
    "packageName": "com.topjohnwu.magisk",
    "category": "System Tools",
    "link": "https://github.com/topjohnwu/Magisk/releases/download/v30.7/Magisk-v30.7.apk",
    "description": "Powerful systemless rooting solution with module support.",
    "icon": "https://raw.githubusercontent.com/LunaDevPH/AppStoreMirror/main/topjohnwo_magisk.png",
    "isVerified": true,
    "isFeatured": true,
    "isSmall": false,
    "hasPreview": false,
    "previewLink": "",
    "version": "30.7",
    "minAndroid": 6,
    "targetAndroid": 15
  },
  {
    "app": "Facebook Lite",
    "creator": "Meta",
    "packageName": "com.facebook.lite",
    "category": "Social",
    "link": "https://raw.githubusercontent.com/LunaDevPH/AppStoreMirror/main/meta_facebooklite.apk",
    "description": "Lightweight Facebook app optimized for low data usage and slower networks.",
    "icon": "https://raw.githubusercontent.com/LunaDevPH/AppStoreMirror/main/meta_facebooklite.png",
    "isVerified": true,
    "isFeatured": false,
    "isSmall": false,
    "hasPreview": false,
    "previewLink": "",
    "version": "500.0.0.8.103",
    "minAndroid": 2.3,
    "targetAndroid": 15
  },
  {
    "app": "LMS Versa",
    "creator": "Mohammed Refat",
    "packageName": "app.lmsversa.android",
    "category": "Education",
    "link": "https://raw.githubusercontent.com/LunaDevPH/AppStoreMirror/main/ams_android_509517_live.apk",
    "description": "Learning management system app for structured academic use.",
    "icon": "https://raw.githubusercontent.com/LunaDevPH/AppStoreMirror/main/app.lmsversa.android_1.0.1_2_icon.png",
    "isVerified": true,
    "isFeatured": true,
    "isSmall": false,
    "hasPreview": false,
    "previewLink": "",
    "version": "1.01",
    "minAndroid": 8,
    "targetAndroid": 14
  },
  {
    "app": "Telegram",
    "creator": "Telegram FZ-LLC",
    "packageName": "org.telegram.messenger",
    "category": "Communication",
    "link": "https://updates.tdesktop.com/android/tandroid.apk",
    "description": "Fast, secure, cloud-based messaging with unlimited chat storage and large group support.",
    "icon": "https://telegram.org/img/t_logo.png",
    "isVerified": true,
    "isFeatured": true,
    "isSmall": false,
    "hasPreview": false,
    "previewLink": "",
    "version": "Latest",
    "minAndroid": 4.4,
    "targetAndroid": 15
  },
  {
    "app": "VLC for Android",
    "creator": "VideoLAN",
    "packageName": "org.videolan.vlc",
    "category": "Media & Video",
    "link": "https://get.videolan.org/vlc-android/3.5.4/VLC-Android-3.5.4-arm64-v8a.apk",
    "description": "Open-source multimedia player supporting nearly all audio and video formats.",
    "icon": "https://f-droid.org/repo/org.videolan.vlc/en-US/icon_yAfSvPRJukZzMMfUzvbYqwaD1XmHXNtiPBtuPVHW-6s%3D.png",
    "isVerified": true,
    "isFeatured": true,
    "isSmall": false,
    "hasPreview": false,
    "previewLink": "",
    "version": "3.5.4",
    "minAndroid": 4.2,
    "targetAndroid": 15
  },
  {
    "app": "Brave Browser",
    "creator": "Brave Software",
    "packageName": "com.brave.browser",
    "category": "Browser",
    "link": "https://github.com/brave/brave-browser/releases/latest/download/BraveMonoarm64.apk",
    "description": "Privacy-focused browser with built-in ad blocking.",
    "icon": "https://upload.wikimedia.org/wikipedia/commons/5/5d/Brave_logo.svg",
    "isVerified": true,
    "isFeatured": true,
    "isSmall": false,
    "hasPreview": false,
    "previewLink": "",
    "version": "Latest",
    "minAndroid": 8,
    "targetAndroid": 15
  },
  {
    "app": "Zoom",
    "creator": "Zoom Video Communications",
    "packageName": "us.zoom.videomeetings",
    "category": "Communication",
    "link": "https://zoom.us/client/latest/zoom.apk",
    "description": "Video conferencing app for meetings and online classes.",
    "icon": "https://upload.wikimedia.org/wikipedia/commons/7/7b/Zoom_Communications_Logo.svg",
    "isVerified": true,
    "isFeatured": false,
    "isSmall": false,
    "hasPreview": false,
    "previewLink": "",
    "version": "Latest",
    "minAndroid": 5,
    "targetAndroid": 15
  },
  {
    "app": "WhatsApp",
    "creator": "Meta",
    "packageName": "com.whatsapp",
    "category": "Communication",
    "link": "https://www.whatsapp.com/android/current/WhatsApp.apk",
    "description": "Popular messaging app with voice and video calls.",
    "icon": "https://upload.wikimedia.org/wikipedia/commons/6/6b/WhatsApp.svg",
    "isVerified": true,
    "isFeatured": true,
    "isSmall": false,
    "hasPreview": false,
    "previewLink": "",
    "version": "Latest",
    "minAndroid": 5,
    "targetAndroid": 15
  },
  {
    "app": "Shizuku",
    "creator": "RikkaApps",
    "packageName": "moe.shizuku.privileged.api",
    "category": "System Tools",
    "link": "https://github.com/RikkaApps/Shizuku/releases/latest/download/Shizuku.apk",
    "description": "Use system-level APIs via ADB without root.",
    "icon": "https://raw.githubusercontent.com/RikkaApps/Shizuku/master/app/src/main/ic_launcher-playstore.png",
    "isVerified": true,
    "isFeatured": false,
    "isSmall": true,
    "hasPreview": false,
    "previewLink": "",
    "version": "Latest",
    "minAndroid": 7,
    "targetAndroid": 15
  },
  {
    "app": "Canta",
    "creator": "Sam Beckman",
    "packageName": "org.samo_lego.canta",
    "category": "System Tools",
    "link": "https://github.com/samolego/Canta/releases/latest/download/Canta.apk",
    "description": "ADB-based debloater app for uninstalling system apps safely.",
    "icon": "https://raw.githubusercontent.com/samolego/Canta/main/fastlane/metadata/android/en-US/images/icon.png",
    "isVerified": true,
    "isFeatured": false,
    "isSmall": true,
    "hasPreview": false,
    "previewLink": "",
    "version": "Latest",
    "minAndroid": 8,
    "targetAndroid": 15
  }
]
